ims/upload/__init__.py
ims/upload/configure.zcml
ims/upload/content.py
ims/upload/indexes.py
ims/upload/interfaces.py
ims/upload/permissions.zcml
ims/upload/setuphandlers.py
ims/upload/testing.py
ims/upload/tools.py
ims/upload/transformable.py
ims/upload/upgrade.py
ims/upload/browser/__init__.py
ims/upload/browser/chunk-view.pt
ims/upload/browser/chunkedfile-view.pt
ims/upload/browser/configure.zcml
ims/upload/browser/content.py
ims/upload/browser/description.pt
ims/upload/browser/factories.py
ims/upload/browser/folderfactories.pt
ims/upload/browser/listing.pt
ims/upload/browser/upload.pt
ims/upload/browser/upload.py
ims/upload/profiles/default/actions.xml
ims/upload/profiles/default/browserlayer.xml
ims/upload/profiles/default/metadata.xml
ims/upload/profiles/default/propertiestool.xml
ims/upload/profiles/default/registry.xml
ims/upload/profiles/default/rolemap.xml
ims/upload/profiles/default/types.xml
ims/upload/profiles/default/workflows.xml
ims/upload/profiles/default/types/Chunk.xml
ims/upload/profiles/default/types/ChunkedFile.xml
ims/upload/profiles/default/types/GroupSpace.xml
ims/upload/profiles/default/workflows/chunkedfile_workflow/definition.xml
ims/upload/profiles/uninstall/actions.xml
ims/upload/profiles/uninstall/browserlayer.xml
ims/upload/profiles/uninstall/registry.xml
ims/upload/profiles/uninstall/types.xml
ims/upload/profiles/uninstall/workflows.xml
ims/upload/static/bootstrap-theme.css
ims/upload/static/bootstrap-theme.css.map
ims/upload/static/bootstrap-theme.less
ims/upload/static/bootstrap.css
ims/upload/static/bootstrap.css.map
ims/upload/static/bootstrap.less
ims/upload/static/chunk.jpg
ims/upload/static/jquery.fileupload.css
ims/upload/static/jquery.fileupload.js
ims/upload/static/upload.css
ims/upload/static/upload.css.map
ims/upload/static/upload.js
ims/upload/static/upload.less
ims/upload/tests/__init__.py
ims/upload/tests/base.py
ims/upload/tests/test_uninstall.py
ims.upload-4.0.0rc2.dist-info/LICENSE
ims.upload-4.0.0rc2.dist-info/METADATA
ims.upload-4.0.0rc2.dist-info/WHEEL
ims.upload-4.0.0rc2.dist-info/entry_points.txt
ims.upload-4.0.0rc2.dist-info/top_level.txt
ims.upload-4.0.0rc2.dist-info/RECORD
